pdspy-2.0.8.dist-info/RECORD
pdspy-2.0.8.dist-info/LICENSE
pdspy-2.0.8.dist-info/WHEEL
pdspy-2.0.8.dist-info/top_level.txt
pdspy-2.0.8.dist-info/METADATA
pdspy-2.0.8.data/scripts/flared_model_dynesty.py
pdspy-2.0.8.data/scripts/generate_surrogate_model.py
pdspy-2.0.8.data/scripts/disk_model_powerlaw.py
pdspy-2.0.8.data/scripts/flared_model_emcee3.py
pdspy-2.0.8.data/scripts/flared_model_nested.py
pdspy-2.0.8.data/scripts/config_template.py
pdspy-2.0.8.data/scripts/disk_model_dynesty.py
pdspy-2.0.8.data/scripts/disk_model_nested.py
pdspy-2.0.8.data/scripts/disk_model_emcee3.py
pdspy-2.0.8.data/scripts/upgrade_to_pdspy2.py
pdspy/__init__.py
pdspy/statistics/ttest.py
pdspy/statistics/__init__.py
pdspy/statistics/fisher_exact.py
pdspy/statistics/Ftest.py
pdspy/statistics/leastsq.py
pdspy/statistics/linear_regression.py
pdspy/statistics/binomial.py
pdspy/misc/dB_nu.py
pdspy/misc/B_nu.py
pdspy/misc/__init__.py
pdspy/misc/gaussian2d.py
pdspy/misc/gaussian.py
pdspy/dust/PAH.py
pdspy/dust/mix_dust.py
pdspy/dust/Dust.py
pdspy/dust/__init__.py
pdspy/dust/run_opacity_tool.py
pdspy/dust/DustGenerator.py
pdspy/dust/redden.py
pdspy/dust/reddening/mcclure.dat
pdspy/dust/reddening/steenman_the.dat
pdspy/dust/reddening/draine_3.1.dat
pdspy/dust/reddening/draine_5.1.dat
pdspy/dust/reddening/draine_4.0.dat
pdspy/dust/data/draine_10um.hdf5
pdspy/dust/data/pollack_1um.hdf5
pdspy/dust/data/diana_1mm.hdf5
pdspy/dust/data/make_diana_wice_100um.py
pdspy/dust/data/diana_10cm.hdf5
pdspy/dust/data/make_diana_wice_1mm.py
pdspy/dust/data/diana_100um.hdf5
pdspy/dust/data/ricci_1um.hdf5
pdspy/dust/data/make_draine_10um.py
pdspy/dust/data/diana_wice.hdf5
pdspy/dust/data/make_diana_1mm.py
pdspy/dust/data/make_diana.py
pdspy/dust/data/make_diana_10um.py
pdspy/dust/data/make_diana_100um.py
pdspy/dust/data/make_diana_10cm.py
pdspy/dust/data/diana_wice_100um.hdf5
pdspy/dust/data/draine_1um.hdf5
pdspy/dust/data/pollack_1mm.hdf5
pdspy/dust/data/draine_3mm.hdf5
pdspy/dust/data/diana_wice_1cm.hdf5
pdspy/dust/data/make_pollack_10cm.py
pdspy/dust/data/diana_1um.hdf5
pdspy/dust/data/make_pollack_10um.py
