Metadata-Version: 2.1
Name: pdspy
Version: 2.0.8
Summary: Radiative transfer modeling of protoplanetary disks
Home-page: https://github.com/psheehan/pdspy
Author: Patrick Sheehan
Author-email: psheehan@northwestern.edu
License-File: LICENSE
Requires-Dist: numpy
Requires-Dist: scipy
Requires-Dist: matplotlib
Requires-Dist: emcee
Requires-Dist: corner
Requires-Dist: hyperion
Requires-Dist: h5py
Requires-Dist: mpi4py
Requires-Dist: Cython
Requires-Dist: astropy
Requires-Dist: schwimmbad
Requires-Dist: dynesty
Requires-Dist: scikit-learn
